kombu_locks
