Metadata-Version: 1.1
Name: kombu-locks
Version: 0.1.1
Summary: Distributed locks implemented with kombu
Home-page: https://github.com/kverdecia/kombu_locks
Author: Karel Antonio Verdecia Ortiz
Author-email: kverdecia@gmail.com
License: MIT license
Keywords: kombu_locks
Platform: UNKNOWN
Classifier: Development Status :: 2 - Pre-Alpha
Classifier: Intended Audience :: Developers
Classifier: License :: OSI Approved :: MIT License
Classifier: Natural Language :: English
Classifier: Programming Language :: Python :: 2.7
Classifier: Programming Language :: Python :: 3
Classifier: Programming Language :: Python :: 3.5
Classifier: Programming Language :: Python :: 3.6
Classifier: Programming Language :: Python :: 3.7
Classifier: Programming Language :: Python :: 3.8
